paypal_easy/__init__.py
paypal_easy/client.py
paypal_easy/django_integration.py
paypal_easy/enums.py
paypal_easy/models.py
test/__init__.py
test/smoke_test.py
test/test_client.py
test/test_models.py
paypal_easy-0.1.8.dist-info/METADATA
paypal_easy-0.1.8.dist-info/WHEEL
paypal_easy-0.1.8.dist-info/top_level.txt
paypal_easy-0.1.8.dist-info/RECORD
